graphs_path_lib/__init__.py
graphs_path_lib/example/__init__.py
graphs_path_lib/example/example.py
graphs_path_lib/src/__init__.py
graphs_path_lib/src/dejkstra.py
graphs_path_lib/src/floyd.py
graphs_path_lib/src/kruskal.py
graphs_path_lib/src/prima.py
graphs_path_lib-0.1.15.dist-info/METADATA
graphs_path_lib-0.1.15.dist-info/WHEEL
graphs_path_lib-0.1.15.dist-info/top_level.txt
graphs_path_lib-0.1.15.dist-info/RECORD
